roboplot/__init__.py
roboplot/base.py
roboplot/graph.py
roboplot/measurements.py
roboplot/robot.py
roboplot/sequence.py
roboplot/trajectory/__init__.py
roboplot/trajectory/three_d.py
roboplot/trajectory/trajectory.py
roboplot/trajectory/two_d.py
roboplot-1.0.3.dist-info/LICENSE
roboplot-1.0.3.dist-info/METADATA
roboplot-1.0.3.dist-info/WHEEL
roboplot-1.0.3.dist-info/top_level.txt
roboplot-1.0.3.dist-info/RECORD
