Metadata-Version: 2.1
Name: roboplot
Version: 1.0.3
Summary: Library of plotting functions for everything robotics
Home-page: https://github.com/borglab/roboplot
Author: Varun Agrawal et. al.
Author-email: varunagrawal@gatech.edu
License: Simplified BSD license
Keywords: robotics plotting prototyping visualization
Platform: any
Classifier: Development Status :: 5 - Production/Stable
Classifier: Intended Audience :: Education
Classifier: Intended Audience :: Developers
Classifier: Intended Audience :: Science/Research
Classifier: Operating System :: MacOS
Classifier: Operating System :: Microsoft :: Windows
Classifier: Operating System :: POSIX
Classifier: License :: OSI Approved :: BSD License
Classifier: Programming Language :: Python :: 3
Requires-Python: >=3.6
License-File: LICENSE
Requires-Dist: daft (>=0.1.0)
Requires-Dist: gtsam (>=4)
Requires-Dist: matplotlib (>=3.3.3)
Requires-Dist: numpy
Requires-Dist: wrapt (>=1.13.0rc3)
